mwx/__init__.py
mwx/bookshelf.py
mwx/controls.py
mwx/framework.py
mwx/graphman.py
mwx/images.py
mwx/matplot2.py
mwx/matplot2g.py
mwx/matplot2lg.py
mwx/mgplt.py
mwx/nutshell.py
mwx/testsuite.py
mwx/utilus.py
mwx/wxmon.py
mwx/wxpdb.py
mwx/wxwil.py
mwx/wxwit.py
mwx/plugins/__init__.py
mwx/plugins/ffmpeg_view.py
mwx/plugins/fft_view.py
mwx/plugins/frame_listview.py
mwx/plugins/line_profile.py
mwx/py/__init__.py
mwx/py/filling.py
mwxlib-1.8.10.dist-info/METADATA
mwxlib-1.8.10.dist-info/WHEEL
mwxlib-1.8.10.dist-info/top_level.txt
mwxlib-1.8.10.dist-info/RECORD
