Metadata-Version: 2.4
Name: mwxlib
Version: 1.8.10
Summary: A wrapper of matplotlib and wxPython (phoenix)
Home-page: https://github.com/komoto48g/mwxlib
Author: Kazuya O'moto
Author-email: komoto@jeol.co.jp
License: MIT
Classifier: Programming Language :: Python :: 3
Classifier: Programming Language :: Python :: 3.8
Classifier: Programming Language :: Python :: 3.9
Classifier: Programming Language :: Python :: 3.10
Classifier: Programming Language :: Python :: 3.11
Classifier: Programming Language :: Python :: 3.12
Classifier: Topic :: Scientific/Engineering :: Image Processing
Classifier: Topic :: Software Development :: Libraries :: Python Modules
Requires-Dist: wxpython>=4.2.0
Requires-Dist: matplotlib
Requires-Dist: opencv-python
Requires-Dist: scipy
Dynamic: author
Dynamic: author-email
Dynamic: classifier
Dynamic: description
Dynamic: description-content-type
Dynamic: home-page
Dynamic: license
Dynamic: requires-dist
Dynamic: summary
